ZhuyunDeJishuGuanlikeWan/README.md
ZhuyunDeJishuGuanlikeWan/__init__.py
ZhuyunDeJishuGuanlikeWan/__main__.py
ZhuyunDeJishuGuanlikeWan/file.epub
ZhuyunDeJishuGuanlikeWan/index.html
ZhuyunDeJishuGuanlikeWan/css/__init__.py
ZhuyunDeJishuGuanlikeWan/css/annotations.css
ZhuyunDeJishuGuanlikeWan/css/main.css
ZhuyunDeJishuGuanlikeWan/css/normalize.css
ZhuyunDeJishuGuanlikeWan/css/popup.css
ZhuyunDeJishuGuanlikeWan/font/__init__.py
ZhuyunDeJishuGuanlikeWan/font/fontello.eot
ZhuyunDeJishuGuanlikeWan/font/fontello.svg
ZhuyunDeJishuGuanlikeWan/font/fontello.ttf
ZhuyunDeJishuGuanlikeWan/font/fontello.woff
ZhuyunDeJishuGuanlikeWan/img/__init__.py
ZhuyunDeJishuGuanlikeWan/img/annotator-glyph-sprite.png
ZhuyunDeJishuGuanlikeWan/img/annotator-icon-sprite.png
ZhuyunDeJishuGuanlikeWan/img/apple-touch-icon.png
ZhuyunDeJishuGuanlikeWan/img/cancelfullscreen.png
ZhuyunDeJishuGuanlikeWan/img/close.png
ZhuyunDeJishuGuanlikeWan/img/fullscreen.png
ZhuyunDeJishuGuanlikeWan/img/loader.gif
ZhuyunDeJishuGuanlikeWan/img/menu-icon.png
ZhuyunDeJishuGuanlikeWan/img/save.png
ZhuyunDeJishuGuanlikeWan/img/saved.png
ZhuyunDeJishuGuanlikeWan/img/settings-s.png
ZhuyunDeJishuGuanlikeWan/img/settings.png
ZhuyunDeJishuGuanlikeWan/img/star.png
ZhuyunDeJishuGuanlikeWan/js/__init__.py
ZhuyunDeJishuGuanlikeWan/js/epub.js
ZhuyunDeJishuGuanlikeWan/js/epub.min.js
ZhuyunDeJishuGuanlikeWan/js/epub.min.map
ZhuyunDeJishuGuanlikeWan/js/hooks.min.js
ZhuyunDeJishuGuanlikeWan/js/hooks.min.map
ZhuyunDeJishuGuanlikeWan/js/reader.js
ZhuyunDeJishuGuanlikeWan/js/reader.js.map
ZhuyunDeJishuGuanlikeWan/js/reader.min.js
ZhuyunDeJishuGuanlikeWan/js/reader.min.map
ZhuyunDeJishuGuanlikeWan/js/hooks/__init__.py
ZhuyunDeJishuGuanlikeWan/js/hooks/extensions/__init__.py
ZhuyunDeJishuGuanlikeWan/js/hooks/extensions/highlight.js
ZhuyunDeJishuGuanlikeWan/js/libs/__init__.py
ZhuyunDeJishuGuanlikeWan/js/libs/jquery.min.js
ZhuyunDeJishuGuanlikeWan/js/libs/localforage.min.js
ZhuyunDeJishuGuanlikeWan/js/libs/screenfull.js
zhuyun_de_jishu_guanlike_wan-2024.3.3.0.dist-info/METADATA
zhuyun_de_jishu_guanlike_wan-2024.3.3.0.dist-info/WHEEL
zhuyun_de_jishu_guanlike_wan-2024.3.3.0.dist-info/entry_points.txt
zhuyun_de_jishu_guanlike_wan-2024.3.3.0.dist-info/top_level.txt
zhuyun_de_jishu_guanlike_wan-2024.3.3.0.dist-info/RECORD
